pathval/__init__.py
pathval/cli.py
pathval-0.1.3.dist-info/METADATA
pathval-0.1.3.dist-info/WHEEL
pathval-0.1.3.dist-info/entry_points.txt
pathval-0.1.3.dist-info/top_level.txt
pathval-0.1.3.dist-info/RECORD
